tests/project/__init__.py
tests/project/models.py
tests/project/management/commands/benchmark.py
tests/project/migrations/0001_initial.py
tests/project/migrations/__init__.py
wagtail_whoosh/__init__.py
wagtail_whoosh/apps.py
wagtail_whoosh/backend.py
wagtail_whoosh/utils.py
wagtail_whoosh-0.2.5.dist-info/DESCRIPTION.rst
wagtail_whoosh-0.2.5.dist-info/METADATA
wagtail_whoosh-0.2.5.dist-info/RECORD
wagtail_whoosh-0.2.5.dist-info/WHEEL
wagtail_whoosh-0.2.5.dist-info/metadata.json
wagtail_whoosh-0.2.5.dist-info/top_level.txt
