Metadata-Version: 2.0
Name: wagtail-whoosh
Version: 0.2.5
Summary: Whoosh backend for Wagtail CMS
Home-page: https://github.com/wagtail/wagtail-whoosh
Author: Michael Yin
Author-email: admin@michaelyin.info
License: BSD License
Platform: UNKNOWN
Classifier: Environment :: Web Environment
Classifier: Framework :: Django
Classifier: Framework :: Wagtail
Classifier: Framework :: Wagtail :: 2
Classifier: Intended Audience :: Developers
Classifier: License :: OSI Approved :: BSD License
Classifier: Operating System :: OS Independent
Classifier: Programming Language :: Python
Classifier: Programming Language :: Python :: 3.4
Classifier: Programming Language :: Python :: 3.5
Classifier: Programming Language :: Python :: 3.6
Classifier: Programming Language :: Python :: 3.7
Classifier: Programming Language :: Python :: 3.8
Classifier: Topic :: Internet :: WWW/HTTP
Classifier: Topic :: Internet :: WWW/HTTP :: Dynamic Content
Requires-Dist: Django (<3.0,>=2.0)
Requires-Dist: Wagtail (<2.8,>=2.3)
Requires-Dist: Whoosh (<2.8,>=2.7)
